TARDIS_Spectrum_Filtering/TARDIS_Spectrum_Filtering.py
TARDIS_Spectrum_Filtering/__init__.py
tardis_spectrum_filtering-1.0.1.dist-info/licenses/LICENSE
tardis_spectrum_filtering-1.0.1.dist-info/METADATA
tardis_spectrum_filtering-1.0.1.dist-info/WHEEL
tardis_spectrum_filtering-1.0.1.dist-info/entry_points.txt
tardis_spectrum_filtering-1.0.1.dist-info/top_level.txt
tardis_spectrum_filtering-1.0.1.dist-info/RECORD
